simple_oauth2/__init__.py
simple_oauth2-1.0.4.dist-info/LICENSE
simple_oauth2-1.0.4.dist-info/METADATA
simple_oauth2-1.0.4.dist-info/WHEEL
simple_oauth2-1.0.4.dist-info/top_level.txt
simple_oauth2-1.0.4.dist-info/RECORD
