Metadata-Version: 2.1
Name: simple_oauth2
Version: 1.0.4
Summary: A simple Outh2 client
Home-page: https://github.com/aminebizid/simple_oauth2
Author: Amine BIZID
Author-email: amine.bizid@gmail.com
License: UNKNOWN
Keywords: Oauth OKTA Azure AD Authentication Authorization token implicit flow
Platform: UNKNOWN
Classifier: Programming Language :: Python :: 3
Classifier: License :: OSI Approved :: MIT License
Classifier: Operating System :: OS Independent
